odoo10_addon_account_fiscal_month-10.0.1.0.0-py2.7-nspkg.pth
odoo/addons/account_fiscal_month/README.rst
odoo/addons/account_fiscal_month/__init__.py
odoo/addons/account_fiscal_month/__manifest__.py
odoo/addons/account_fiscal_month/data/date_range_type.xml
odoo/addons/account_fiscal_month/models/__init__.py
odoo/addons/account_fiscal_month/models/date_range_type.py
odoo/addons/account_fiscal_month/models/res_company.py
odoo/addons/account_fiscal_month/static/description/icon.png
odoo/addons/account_fiscal_month/tests/__init__.py
odoo/addons/account_fiscal_month/tests/test_account_fiscal_month.py
odoo/addons/account_fiscal_month/views/date_range_type.xml
odoo10_addon_account_fiscal_month-10.0.1.0.0.dist-info/DESCRIPTION.rst
odoo10_addon_account_fiscal_month-10.0.1.0.0.dist-info/METADATA
odoo10_addon_account_fiscal_month-10.0.1.0.0.dist-info/RECORD
odoo10_addon_account_fiscal_month-10.0.1.0.0.dist-info/WHEEL
odoo10_addon_account_fiscal_month-10.0.1.0.0.dist-info/metadata.json
odoo10_addon_account_fiscal_month-10.0.1.0.0.dist-info/namespace_packages.txt
odoo10_addon_account_fiscal_month-10.0.1.0.0.dist-info/top_level.txt
